{"Tongan":"Τόγκα","Fijian":"Φίτζι","Swedish":"Σουηδικά","French":"Γαλλικά","Maltese":"Μαλτεζικά","Afrikaans":"Αφρικάανς","Telugu":"Τελουγκουικά","Urdu":"Ουρντού","Bangla":"Bangla","Philippines":"Φιλιππίνες","Greek":"Ελληνικά","Tahitian":"Tahitian","Samoan":"Σαμόα","Italian":"Ιταλικά","Welsh":"Ουαλλικά","Swahili":"Σουαχίλι","Arabic":"Αραβικά","Hungarian":"Ουγγρικά","Bulgarian":"Βουλγαρικά","Croatian":"Κροατικά","Portuguese":"Πορτογαλικά","Querétaro Otomi":"Κερετάρο Οτόμι","Russian":"Ρωσικά","Icelandic":"Ισλανδικά","Cantonese (Traditional)":"Καντονέζικη (παραδοσιακή)","Spanish":"Ισπανικά","Turkish":"Τουρκικά","Prompt":"Επιλογή γλώσσας για","Yucatec Maya":"Γιουάτεκ Μάγια","Danish":"Δανικά","Latvian":"Λετονικά","German":"Γερμανικά","Hebrew":"Εβραϊκά","Bosnian":"Βοσνιακά","Hmong Daw":"Πολύ γλυκό.","Lithuanian":"Λιθουανικά","Slovak":"Σλοβακικά","Japanese":"Ιαπωνικά","Polish":"Πολωνικά","Tamil":"Ταμιλικά","Catalan":"Καταλανικά","Thai":"Ταϊλανδικά","Korean":"Κορεατικά","Romanian":"Ρουμανικά","Malagasy":"Μαδαγασκάρης","Norwegian":"Νορβηγικά","Serbian (Cyrillic)":"Σερβικά (Κυριλλικά)","Serbian (Latin)":"Σερβικά (Λατινικά)","Ukrainian":"Ουκρανικά","English":"Αγγλικά","Estonian":"Εσθονικά","Czech":"Τσεχικά","Vietnamese":"Βιετναμικά","Indonesian":"Ινδονησιακά","Chinese Simplified":"Απλοποιημένα κινεζικά","Dutch":"Ολλανδικά","Hindi":"Δεν","Persian":"Περσικά","Slovenian":"Σλοβενικά","Haitian Creole":"γλώσσα Αϊτής","Finnish":"Φινλανδικά","Chinese Traditional":"Παραδοσιακά κινεζικά"}