{"Tongan":"Tonga","Fijian":"Fijian","Swedish":"Szwedzki","French":"Francuski","Maltese":"Maltański","Afrikaans":"Afrikaans","Telugu":"Telugu","Urdu":"Urdu","Bangla":"Bangla","Philippines":"Filipiny","Greek":"Grecki","Tahitian":"Tahitian","Samoan":"Samoański","Italian":"Włoski","Welsh":"Walijski","Swahili":"Suahili","Arabic":"Arabski","Hungarian":"Węgierski","Bulgarian":"Bułgarski","Croatian":"Chorwacki","Portuguese":"Portugalski","Querétaro Otomi":"Queretaro Otomi","Russian":"Rosyjski","Icelandic":"Islandzki","Cantonese (Traditional)":"Kantoński (tradycyjny)","Spanish":"Hiszpański","Turkish":"Turecki","Prompt":"Wybierz język dla","Yucatec Maya":"Yucatec Maya","Danish":"Duński","Latvian":"Łotewski","German":"Niemiecki","Hebrew":"Hebrajski","Bosnian":"Bośniacki","Hmong Daw":"Hmong DAW","Lithuanian":"Litewski","Slovak":"Słowacki","Japanese":"Japoński","Polish":"Polski","Tamil":"Tamilski","Catalan":"Kataloński","Thai":"Tajski","Korean":"Koreański","Romanian":"Rumuński","Malagasy":"Madagaskaru","Norwegian":"Norweski","Serbian (Cyrillic)":"Serbski (Cyrylica)","Serbian (Latin)":"Serbski (łaciński)","Ukrainian":"Ukraiński","English":"Angielski","Estonian":"Estoński","Czech":"Czeski","Vietnamese":"Wietnamski","Indonesian":"Indonezyjski","Chinese Simplified":"Chiński uproszczony","Dutch":"Holenderski","Hindi":"Nie","Persian":"Perski","Slovenian":"Słoweński","Haitian Creole":"Haitański","Finnish":"Fiński","Chinese Traditional":"Chiński tradycyjny"}